{
	"backtraceGraph" : 
	{
		"commands" : 
		[
			"install",
			"POCO_INSTALL",
			"POCO_GENERATE_PACKAGE"
		],
		"files" : 
		[
			"poco/cmake/PocoMacros.cmake",
			"poco/XML/CMakeLists.txt"
		],
		"nodes" : 
		[
			{
				"file" : 1
			},
			{
				"command" : 1,
				"file" : 1,
				"line" : 65,
				"parent" : 0
			},
			{
				"command" : 0,
				"file" : 0,
				"line" : 265,
				"parent" : 1
			},
			{
				"command" : 0,
				"file" : 0,
				"line" : 272,
				"parent" : 1
			},
			{
				"command" : 2,
				"file" : 1,
				"line" : 66,
				"parent" : 0
			},
			{
				"command" : 0,
				"file" : 0,
				"line" : 239,
				"parent" : 4
			},
			{
				"command" : 0,
				"file" : 0,
				"line" : 246,
				"parent" : 4
			}
		]
	},
	"installers" : 
	[
		{
			"backtrace" : 2,
			"component" : "Devel",
			"destination" : "include",
			"paths" : 
			[
				"poco/XML/include/Poco"
			],
			"type" : "directory"
		},
		{
			"backtrace" : 3,
			"component" : "Unspecified",
			"destination" : "lib",
			"paths" : 
			[
				"lib/libPocoXML.so.94"
			],
			"targetId" : "XML::@407a09694fa2df365393",
			"targetIndex" : 19,
			"targetInstallNamelink" : "skip",
			"type" : "target"
		},
		{
			"backtrace" : 3,
			"component" : "Unspecified",
			"destination" : "lib",
			"paths" : 
			[
				"lib/libPocoXML.so"
			],
			"targetId" : "XML::@407a09694fa2df365393",
			"targetIndex" : 19,
			"targetInstallNamelink" : "only",
			"type" : "target"
		},
		{
			"backtrace" : 5,
			"component" : "Unspecified",
			"destination" : "lib/cmake/Poco",
			"exportName" : "XMLTargets",
			"exportTargets" : 
			[
				{
					"id" : "XML::@407a09694fa2df365393",
					"index" : 19
				}
			],
			"paths" : 
			[
				"poco/XML/CMakeFiles/Export/lib/cmake/Poco/PocoXMLTargets.cmake"
			],
			"type" : "export"
		},
		{
			"backtrace" : 6,
			"component" : "Devel",
			"destination" : "lib/cmake/Poco",
			"paths" : 
			[
				"build/Poco/PocoXMLConfig.cmake",
				"build/Poco/PocoXMLConfigVersion.cmake"
			],
			"type" : "file"
		}
	],
	"paths" : 
	{
		"build" : "poco/XML",
		"source" : "poco/XML"
	}
}
